readdbc/__init__.py
readdbc/blast/blast-dbf.c
readdbc/blast/blast.c
readdbc/blast/blast.h
readdbc/blast-dbf
readdbc-0.2.0.dist-info/LICENSE
readdbc-0.2.0.dist-info/METADATA
readdbc-0.2.0.dist-info/WHEEL
readdbc-0.2.0.dist-info/RECORD
