Metadata-Version: 2.1
Name: readdbc
Version: 0.2.0
Summary: Ler arquivos .dbc do datasus
License: MIT
Author: Edson (edinho)
Requires-Python: >=3.8,<4.0
Classifier: License :: OSI Approved :: MIT License
Classifier: Programming Language :: Python :: 3
Classifier: Programming Language :: Python :: 3.8
Classifier: Programming Language :: Python :: 3.9
Classifier: Programming Language :: Python :: 3.10
Classifier: Programming Language :: Python :: 3.11
Classifier: Programming Language :: Python :: 3.12
Requires-Dist: cffi (>=1.16.0,<2.0.0)
Requires-Dist: setuptools (>=56)
Requires-Dist: simpledbf (>=0.2.6,<0.3.0)
